gravity_auto_exit/__init__.py
gravity_auto_exit/logger.py
gravity_auto_exit/main.py
gravity_auto_exit/settings.py
gravity_auto_exit/logs/__init__.py
gravity_auto_exit-1.71.3.dist-info/LICENSE
gravity_auto_exit-1.71.3.dist-info/METADATA
gravity_auto_exit-1.71.3.dist-info/WHEEL
gravity_auto_exit-1.71.3.dist-info/top_level.txt
gravity_auto_exit-1.71.3.dist-info/RECORD
