Metadata-Version: 2.1
Name: gravity-auto-exit
Version: 1.71.3
Author: PunchyArchy
Author-email: ksmdrmvscthny@gmail.com
License-File: LICENSE
Requires-Dist: qcad (==0.7.2)
Requires-Dist: whikoperator
Requires-Dist: pillow
Requires-Dist: qneuroworker (>=1.0.7)
